poetry_demo_lib/__init__.py
poetry_demo_lib/hello.py
poetry_demo_lib-0.3.0.dist-info/WHEEL
poetry_demo_lib-0.3.0.dist-info/METADATA
poetry_demo_lib-0.3.0.dist-info/RECORD
