Metadata-Version: 2.1
Name: poetry-demo-lib
Version: 0.3.0
Summary: test poetry library publishing
Author: webee.yw
Author-email: webee.yw@gmail.com
Requires-Python: >=3.9,<4.0
Classifier: Programming Language :: Python :: 3
Classifier: Programming Language :: Python :: 3.9
